[{"name":"MARIANA TRONIX","cpf":"496.310.720-10","birthdate":"11/05/1998","balance":700,"extract":[{"value":700,"data":"06/06/2022 14:49","description":"Transverencia entre contas da mesma Instituição"}]},{"name":"ADEIR MOREIRA MAIA","cpf":"712.982.429-88","birthdate":"12/12/1994","balance":1667,"extract":[{"value":4000,"data":"06/06/2022 14:29","description":"Depósito em Dinheiro."},{"value":-675,"data":"06/06/2022 14:44","description":"Transverencia entre contas da mesma Instituição"},{"value":-233,"data":"06/06/2022","description":"fatura cartão de crédito"},{"value":-675,"data":"06/06/2022 14:47","description":"Transverencia entre contas da mesma Instituição"},{"value":-50,"data":"06/06/2022 14:48","description":"Transverencia entre contas da mesma Instituição"},{"value":-700,"data":"06/06/2022 14:49","description":"Transverencia entre contas da mesma Instituição"}]},{"name":"ERIC SILVA E SILVA","cpf":"456.046.560-62","birthdate":"30/05/2003","balance":600,"extract":[{"value":675,"data":"06/06/2022 14:44","description":"Transverencia entre contas da mesma Instituição"},{"value":-75,"data":"06/06/2022","description":"Compra de Skill de valorant"}]},{"name":"ARIANE TIER DE MELLO","cpf":"123.456.789-12","birthdate":"21/07/1993","balance":275,"extract":[{"value":675,"data":"06/06/2022 14:47","description":"Transverencia entre contas da mesma Instituição"},{"value":-400,"data":"06/06/2022","description":"Pagamento mensal Ifood"}]},{"name":"EDUARDO OSIRO","cpf":"960.150.180-03","birthdate":"15/09/1989","balance":50,"extract":[{"value":50,"data":"06/06/2022 14:48","description":"Transverencia entre contas da mesma Instituição"}]}]